finoptions/__init__.py
finoptions/base.py
finoptions/base_test.py
finoptions/utils.py
finoptions/vanillaoptions.py
finoptions/basic_american_options/__init__.py
finoptions/binomial_tree_options/__init__.py
finoptions/heston_nandi_options/__init__.py
finoptions/heston_nandi_options/hnGARCH.py
finoptions/monte_carlo_options/__init__.py
finoptions/monte_carlo_options/mc_innovations.py
finoptions/monte_carlo_options/mc_paths.py
finoptions/monte_carlo_options/mc_payoffs.py
finoptions/spread_options/__init__.py
finoptions/spread_options/bitree3d.py
finoptions/spread_options/spreadapprox.py
finoptions/spread_options/tree_spread.py
finoptions-0.1.5.dist-info/LICENSE
finoptions-0.1.5.dist-info/METADATA
finoptions-0.1.5.dist-info/WHEEL
finoptions-0.1.5.dist-info/top_level.txt
finoptions-0.1.5.dist-info/RECORD
