Metadata-Version: 2.1
Name: finoptions
Version: 0.1.5
Summary: Energy derivatives (futures, options etc...)
Home-page: https://github.com/bbcho/finoptions-dev
Author: Ben Cho
Author-email: ben.cho@gmail.com
License: MIT License
Keywords: Energy,Risk,Crude,Trading,Petroleum,Oil,Refinery,Refined Products,Products
Platform: UNKNOWN
Classifier: Development Status :: 3 - Alpha
Classifier: License :: OSI Approved :: MIT License
Classifier: Programming Language :: Python :: 3
Classifier: Operating System :: OS Independent
Classifier: Intended Audience :: Financial and Insurance Industry
Requires-Python: >=3.6
License-File: LICENSE
Requires-Dist: scipy (>=1.7)
Requires-Dist: numpy
Requires-Dist: numdifftools
Requires-Dist: matplotlib
